deprecated/mh copy.py
deprecated/mh_new.py
deprecated/run copy.py
deprecated/utils copy.py
pysaebm/__init__.py
pysaebm/data_generate.py
pysaebm/kde_mh.py
pysaebm/kde_utils.py
pysaebm/mh.py
pysaebm/run.py
pysaebm/utils.py
pysaebm/viz.py
pysaebm/data/__init__.py
pysaebm/data/params.json
pysaebm/data/samples/10|100_0.csv
pysaebm/data/samples/5|50_0.csv
pysaebm/test/gen.py
pysaebm/test/test.py
pysaebm-7.7.2.dist-info/licenses/LICENSE
pysaebm-7.7.2.dist-info/METADATA
pysaebm-7.7.2.dist-info/WHEEL
pysaebm-7.7.2.dist-info/top_level.txt
pysaebm-7.7.2.dist-info/RECORD
